depviz/__init__.py
depviz/cli.py
depviz/graph.py
depviz/utils.py
depviz/parsers/__init__.py
depviz/parsers/bazel_parser.py
depviz/parsers/package_json_parser.py
depviz/parsers/requirements_parser.py
depviz-1.0.6.dist-info/METADATA
depviz-1.0.6.dist-info/WHEEL
depviz-1.0.6.dist-info/entry_points.txt
depviz-1.0.6.dist-info/top_level.txt
depviz-1.0.6.dist-info/RECORD
