Metadata-Version: 2.1
Name: depviz
Version: 1.0.6
Summary: Quick Dependency Graph Viewer
Home-page: https://github.com/yourusername/depviz
Author: Your Name
Author-email: your.email@example.com
Classifier: Programming Language :: Python :: 3
Classifier: License :: OSI Approved :: MIT License
Classifier: Operating System :: OS Independent
Requires-Python: >=3.6
Requires-Dist: click>=7.0
Requires-Dist: graphviz>=0.14
